imutil/DejaVuSansMono.ttf
imutil/__init__.py
imutil-0.3.4.dist-info/LICENSE
imutil-0.3.4.dist-info/METADATA
imutil-0.3.4.dist-info/WHEEL
imutil-0.3.4.dist-info/top_level.txt
imutil-0.3.4.dist-info/RECORD
