Metadata-Version: 2.1
Name: imutil
Version: 0.3.4
Summary: Flexible utility for displaying images
Home-page: https://github.com/lwneal/imutil
Author: Larry Neal
Author-email: nealla@lwneal.com
License: UNKNOWN
Platform: UNKNOWN
Requires-Python: >3
License-File: LICENSE
Requires-Dist: Pillow
Requires-Dist: numpy
Requires-Dist: scikit-image
